<?xml version="1.0" encoding="UTF-8"?>
<!DOCTYPE mapper PUBLIC "-//mybatis.org//DTD Mapper 3.0//EN" "http://mybatis.org/dtd/mybatis-3-mapper.dtd">
<mapper namespace="cn.amy.user.dao.mapper.CustPersonMapper">
  <resultMap id="BaseResultMap" type="cn.amy.user.entity.CustPerson">
    <!--
      WARNING - @mbggenerated
      This element is automatically generated by MyBatis Generator, do not modify.
    -->
    <result column="landlord_id" jdbcType="VARCHAR" property="landlordId" />
    <result column="user_id" jdbcType="VARCHAR" property="userId" />
    <result column="NAME" jdbcType="VARCHAR" property="name" />
    <result column="alias" jdbcType="VARCHAR" property="alias" />
    <result column="english_name" jdbcType="VARCHAR" property="englishName" />
    <result column="MOBILE_PHONE" jdbcType="VARCHAR" property="mobilePhone" />
    <result column="ID_NO" jdbcType="VARCHAR" property="idNo" />
    <result column="ID_FROM_DATE" jdbcType="DATE" property="idFromDate" />
    <result column="ID_THRU_DATE" jdbcType="DATE" property="idThruDate" />
    <result column="FRONT_CONTENT_ID" jdbcType="VARCHAR" property="frontContentId" />
    <result column="BACK_CONTENT_ID" jdbcType="VARCHAR" property="backContentId" />
    <result column="IDENTIFICATION_ID" jdbcType="BIGINT" property="identificationId" />
    <result column="PROVINCE" jdbcType="VARCHAR" property="province" />
    <result column="CITY" jdbcType="VARCHAR" property="city" />
    <result column="DISTRICT" jdbcType="VARCHAR" property="district" />
    <result column="ADDRESS" jdbcType="VARCHAR" property="address" />
    <result column="EDUCATION_ENUM" jdbcType="VARCHAR" property="educationEnum" />
    <result column="DEGREE_ENUM" jdbcType="VARCHAR" property="degreeEnum" />
    <result column="introduce" jdbcType="VARCHAR" property="introduce" />
    <result column="type" jdbcType="VARCHAR" property="type" />
    <result column="head_url" jdbcType="VARCHAR" property="headUrl" />
    <result column="MARRAGE_ENUM" jdbcType="VARCHAR" property="marrageEnum" />
    <result column="OCCUPATION_ENUM" jdbcType="VARCHAR" property="occupationEnum" />
    <result column="TITLE_ENUM" jdbcType="VARCHAR" property="titleEnum" />
    <result column="PTITLE_ENUM" jdbcType="VARCHAR" property="ptitleEnum" />
    <result column="WORKING_UNIT" jdbcType="VARCHAR" property="workingUnit" />
    <result column="INDUSTRY_ENUM" jdbcType="VARCHAR" property="industryEnum" />
    <result column="EMAIL" jdbcType="VARCHAR" property="email" />
    <result column="ACCOUNT_NO" jdbcType="VARCHAR" property="accountNo" />
    <result column="ACCOUNT_MOBILE_PHONE" jdbcType="VARCHAR" property="accountMobilePhone" />
    <result column="CREATE_BY" jdbcType="VARCHAR" property="createBy" />
    <result column="CREATE_TIME" jdbcType="TIMESTAMP" property="createTime" />
    <result column="LAST_MODIFIED_BY" jdbcType="VARCHAR" property="lastModifiedBy" />
    <result column="LAST_MODIFIED_TIME" jdbcType="TIMESTAMP" property="lastModifiedTime" />
    <result column="LAST_MODIFIED_SEQ" jdbcType="BIGINT" property="lastModifiedSeq" />
    <result column="QQ_NO" jdbcType="VARCHAR" property="qqNo" />
    <result column="WEECHAT_NO" jdbcType="VARCHAR" property="weechatNo" />
  </resultMap>
  <insert id="insert" parameterType="cn.amy.user.entity.CustPerson">
    <!--
      WARNING - @mbggenerated
      This element is automatically generated by MyBatis Generator, do not modify.
    -->
    insert into CUST_PERSON (landlord_id, user_id, NAME, 
      alias, english_name, MOBILE_PHONE, 
      ID_NO, ID_FROM_DATE, ID_THRU_DATE, 
      FRONT_CONTENT_ID, BACK_CONTENT_ID, IDENTIFICATION_ID, 
      PROVINCE, CITY, DISTRICT, 
      ADDRESS, EDUCATION_ENUM, DEGREE_ENUM, 
      introduce, type, head_url, 
      MARRAGE_ENUM, OCCUPATION_ENUM, TITLE_ENUM, 
      PTITLE_ENUM, WORKING_UNIT, INDUSTRY_ENUM, 
      EMAIL, ACCOUNT_NO, ACCOUNT_MOBILE_PHONE, 
      CREATE_BY, CREATE_TIME, LAST_MODIFIED_BY, 
      LAST_MODIFIED_TIME, LAST_MODIFIED_SEQ, QQ_NO, 
      WEECHAT_NO)
    values (#{landlordId,jdbcType=VARCHAR}, #{userId,jdbcType=VARCHAR}, #{name,jdbcType=VARCHAR}, 
      #{alias,jdbcType=VARCHAR}, #{englishName,jdbcType=VARCHAR}, #{mobilePhone,jdbcType=VARCHAR}, 
      #{idNo,jdbcType=VARCHAR}, #{idFromDate,jdbcType=DATE}, #{idThruDate,jdbcType=DATE}, 
      #{frontContentId,jdbcType=VARCHAR}, #{backContentId,jdbcType=VARCHAR}, #{identificationId,jdbcType=BIGINT}, 
      #{province,jdbcType=VARCHAR}, #{city,jdbcType=VARCHAR}, #{district,jdbcType=VARCHAR}, 
      #{address,jdbcType=VARCHAR}, #{educationEnum,jdbcType=VARCHAR}, #{degreeEnum,jdbcType=VARCHAR}, 
      #{introduce,jdbcType=VARCHAR}, #{type,jdbcType=VARCHAR}, #{headUrl,jdbcType=VARCHAR}, 
      #{marrageEnum,jdbcType=VARCHAR}, #{occupationEnum,jdbcType=VARCHAR}, #{titleEnum,jdbcType=VARCHAR}, 
      #{ptitleEnum,jdbcType=VARCHAR}, #{workingUnit,jdbcType=VARCHAR}, #{industryEnum,jdbcType=VARCHAR}, 
      #{email,jdbcType=VARCHAR}, #{accountNo,jdbcType=VARCHAR}, #{accountMobilePhone,jdbcType=VARCHAR}, 
      #{createBy,jdbcType=VARCHAR}, #{createTime,jdbcType=TIMESTAMP}, #{lastModifiedBy,jdbcType=VARCHAR}, 
      #{lastModifiedTime,jdbcType=TIMESTAMP}, #{lastModifiedSeq,jdbcType=BIGINT}, #{qqNo,jdbcType=VARCHAR}, 
      #{weechatNo,jdbcType=VARCHAR})
  </insert>
  <insert id="insertSelective" parameterType="cn.amy.user.entity.CustPerson">
    <!--
      WARNING - @mbggenerated
      This element is automatically generated by MyBatis Generator, do not modify.
    -->
    insert into CUST_PERSON
    <trim prefix="(" suffix=")" suffixOverrides=",">
      <if test="landlordId != null">
        landlord_id,
      </if>
      <if test="userId != null">
        user_id,
      </if>
      <if test="name != null">
        NAME,
      </if>
      <if test="alias != null">
        alias,
      </if>
      <if test="englishName != null">
        english_name,
      </if>
      <if test="mobilePhone != null">
        MOBILE_PHONE,
      </if>
      <if test="idNo != null">
        ID_NO,
      </if>
      <if test="idFromDate != null">
        ID_FROM_DATE,
      </if>
      <if test="idThruDate != null">
        ID_THRU_DATE,
      </if>
      <if test="frontContentId != null">
        FRONT_CONTENT_ID,
      </if>
      <if test="backContentId != null">
        BACK_CONTENT_ID,
      </if>
      <if test="identificationId != null">
        IDENTIFICATION_ID,
      </if>
      <if test="province != null">
        PROVINCE,
      </if>
      <if test="city != null">
        CITY,
      </if>
      <if test="district != null">
        DISTRICT,
      </if>
      <if test="address != null">
        ADDRESS,
      </if>
      <if test="educationEnum != null">
        EDUCATION_ENUM,
      </if>
      <if test="degreeEnum != null">
        DEGREE_ENUM,
      </if>
      <if test="introduce != null">
        introduce,
      </if>
      <if test="type != null">
        type,
      </if>
      <if test="headUrl != null">
        head_url,
      </if>
      <if test="marrageEnum != null">
        MARRAGE_ENUM,
      </if>
      <if test="occupationEnum != null">
        OCCUPATION_ENUM,
      </if>
      <if test="titleEnum != null">
        TITLE_ENUM,
      </if>
      <if test="ptitleEnum != null">
        PTITLE_ENUM,
      </if>
      <if test="workingUnit != null">
        WORKING_UNIT,
      </if>
      <if test="industryEnum != null">
        INDUSTRY_ENUM,
      </if>
      <if test="email != null">
        EMAIL,
      </if>
      <if test="accountNo != null">
        ACCOUNT_NO,
      </if>
      <if test="accountMobilePhone != null">
        ACCOUNT_MOBILE_PHONE,
      </if>
      <if test="createBy != null">
        CREATE_BY,
      </if>
      <if test="createTime != null">
        CREATE_TIME,
      </if>
      <if test="lastModifiedBy != null">
        LAST_MODIFIED_BY,
      </if>
      <if test="lastModifiedTime != null">
        LAST_MODIFIED_TIME,
      </if>
      <if test="lastModifiedSeq != null">
        LAST_MODIFIED_SEQ,
      </if>
      <if test="qqNo != null">
        QQ_NO,
      </if>
      <if test="weechatNo != null">
        WEECHAT_NO,
      </if>
    </trim>
    <trim prefix="values (" suffix=")" suffixOverrides=",">
      <if test="landlordId != null">
        #{landlordId,jdbcType=VARCHAR},
      </if>
      <if test="userId != null">
        #{userId,jdbcType=VARCHAR},
      </if>
      <if test="name != null">
        #{name,jdbcType=VARCHAR},
      </if>
      <if test="alias != null">
        #{alias,jdbcType=VARCHAR},
      </if>
      <if test="englishName != null">
        #{englishName,jdbcType=VARCHAR},
      </if>
      <if test="mobilePhone != null">
        #{mobilePhone,jdbcType=VARCHAR},
      </if>
      <if test="idNo != null">
        #{idNo,jdbcType=VARCHAR},
      </if>
      <if test="idFromDate != null">
        #{idFromDate,jdbcType=DATE},
      </if>
      <if test="idThruDate != null">
        #{idThruDate,jdbcType=DATE},
      </if>
      <if test="frontContentId != null">
        #{frontContentId,jdbcType=VARCHAR},
      </if>
      <if test="backContentId != null">
        #{backContentId,jdbcType=VARCHAR},
      </if>
      <if test="identificationId != null">
        #{identificationId,jdbcType=BIGINT},
      </if>
      <if test="province != null">
        #{province,jdbcType=VARCHAR},
      </if>
      <if test="city != null">
        #{city,jdbcType=VARCHAR},
      </if>
      <if test="district != null">
        #{district,jdbcType=VARCHAR},
      </if>
      <if test="address != null">
        #{address,jdbcType=VARCHAR},
      </if>
      <if test="educationEnum != null">
        #{educationEnum,jdbcType=VARCHAR},
      </if>
      <if test="degreeEnum != null">
        #{degreeEnum,jdbcType=VARCHAR},
      </if>
      <if test="introduce != null">
        #{introduce,jdbcType=VARCHAR},
      </if>
      <if test="type != null">
        #{type,jdbcType=VARCHAR},
      </if>
      <if test="headUrl != null">
        #{headUrl,jdbcType=VARCHAR},
      </if>
      <if test="marrageEnum != null">
        #{marrageEnum,jdbcType=VARCHAR},
      </if>
      <if test="occupationEnum != null">
        #{occupationEnum,jdbcType=VARCHAR},
      </if>
      <if test="titleEnum != null">
        #{titleEnum,jdbcType=VARCHAR},
      </if>
      <if test="ptitleEnum != null">
        #{ptitleEnum,jdbcType=VARCHAR},
      </if>
      <if test="workingUnit != null">
        #{workingUnit,jdbcType=VARCHAR},
      </if>
      <if test="industryEnum != null">
        #{industryEnum,jdbcType=VARCHAR},
      </if>
      <if test="email != null">
        #{email,jdbcType=VARCHAR},
      </if>
      <if test="accountNo != null">
        #{accountNo,jdbcType=VARCHAR},
      </if>
      <if test="accountMobilePhone != null">
        #{accountMobilePhone,jdbcType=VARCHAR},
      </if>
      <if test="createBy != null">
        #{createBy,jdbcType=VARCHAR},
      </if>
      <if test="createTime != null">
        #{createTime,jdbcType=TIMESTAMP},
      </if>
      <if test="lastModifiedBy != null">
        #{lastModifiedBy,jdbcType=VARCHAR},
      </if>
      <if test="lastModifiedTime != null">
        #{lastModifiedTime,jdbcType=TIMESTAMP},
      </if>
      <if test="lastModifiedSeq != null">
        #{lastModifiedSeq,jdbcType=BIGINT},
      </if>
      <if test="qqNo != null">
        #{qqNo,jdbcType=VARCHAR},
      </if>
      <if test="weechatNo != null">
        #{weechatNo,jdbcType=VARCHAR},
      </if>
    </trim>
  </insert>
</mapper>